differtless/__init__.py
differtless/ad.py
differtless/operations.py
differtless-0.0.1.dist-info/LICENSE
differtless-0.0.1.dist-info/METADATA
differtless-0.0.1.dist-info/WHEEL
differtless-0.0.1.dist-info/top_level.txt
differtless-0.0.1.dist-info/RECORD
