Metadata-Version: 2.1
Name: differtless
Version: 0.0.1
Summary: Package for (effortless) automatic differentiation in Python
Home-page: https://github.com/differtless/cs107-FinalProject
Author: Anastasia Ershova, Mark Penrod, Will Wang, Teresa Datta
Author-email: aershova@g.harvard.edu, mpenrod@g.harvard.edu, willwang@g.harvard.edu, tdatta@g.harvard.edu
License: UNKNOWN
Platform: UNKNOWN
Classifier: Programming Language :: Python :: 3
Classifier: License :: OSI Approved :: MIT License
Classifier: Operating System :: OS Independent
Requires-Python: >=3.6
